tokens_example/core/__init__.py
tokens_example/core/settings.py
tokens_example/core/urls.py
tokens_example/db.sqlite3
tokens_example/manage.py
tokens_example/tokens/__init__.py
tokens_example/tokens/apps.py
tokens_example/tokens/generation.py
tokens_example/tokens/management/__init__.py
tokens_example/tokens/management/commands/__init__.py
tokens_example/tokens/management/commands/delete_expired_tokens.py
tokens_example/tokens/migrations/0001_initial.py
tokens_example/tokens/migrations/__init__.py
tokens_example/tokens/models.py
tokens_example/tokens/utils.py
django_verification_example-0.1.0.dist-info/WHEEL
django_verification_example-0.1.0.dist-info/METADATA
django_verification_example-0.1.0.dist-info/RECORD
